{
  "routes": [
    {
      "method": "GET",
      "path": "/api/media",
      "handler": "Media.find",
      "config": {
        "policies": []
      }
    },
    {
      "method": "GET",
      "path": "/api/media/count",
      "handler": "Media.count",
      "config": {
        "policies": []
      }
    },
    {
      "method": "GET",
      "path": "/api/media/:_id",
      "handler": "Media.findOne",
      "config": {
        "policies": []
      }
    },
    {
      "method": "POST",
      "path": "/api/media",
      "handler": "Media.create",
      "config": {
        "policies": []
      }
    },
    {
      "method": "PUT",
      "path": "/api/media/:_id",
      "handler": "Media.update",
      "config": {
        "policies": []
      }
    },
    {
      "method": "DELETE",
      "path": "/api/media/:_id",
      "handler": "Media.destroy",
      "config": {
        "policies": []
      }
    }
  ]
}